paulmann/__init__.py
paulmann/const.py
paulmann/exceptions.py
paulmann/models.py
paulmann/paulmann.py
paulmann-0.1.0.dist-info/LICENSE
paulmann-0.1.0.dist-info/METADATA
paulmann-0.1.0.dist-info/WHEEL
paulmann-0.1.0.dist-info/top_level.txt
paulmann-0.1.0.dist-info/RECORD
