Metadata-Version: 2.1
Name: paulmann
Version: 0.1.0
Summary: lib for accessing Paulmann Lichts BLE enabled lights
Home-page: UNKNOWN
Author: mjekovec
Author-email: UNKNOWN
License: MIT
Platform: UNKNOWN
Classifier: Programming Language :: Python
Classifier: Programming Language :: Python :: 3.7
